main.py
cubespec_puna-0.1.0.dist-info/METADATA
cubespec_puna-0.1.0.dist-info/WHEEL
cubespec_puna-0.1.0.dist-info/top_level.txt
cubespec_puna-0.1.0.dist-info/RECORD
