Metadata-Version: 2.4
Name: cubespec-puna
Version: 0.1.0
Summary: Control the PUNA Hexapod for positioning cubespec optics
Requires-Python: >=3.12
Requires-Dist: symetrie-hexapod
